.gitignore
Plugin.py
SchemaExtension.py
TaskResult.py
__init__.py
constants.py
pyproject.toml
schema.py
utils.py
owe_python_sdk-0.0.1.dist-info/WHEEL
owe_python_sdk-0.0.1.dist-info/METADATA
owe_python_sdk-0.0.1.dist-info/RECORD
